setup.py
HackerNewsAPI/API.py
HackerNewsAPI/__init__.py
HackerNewsAPI/utils.py
HackerNewsAPI.egg-info/PKG-INFO
HackerNewsAPI.egg-info/SOURCES.txt
HackerNewsAPI.egg-info/dependency_links.txt
HackerNewsAPI.egg-info/requires.txt
HackerNewsAPI.egg-info/top_level.txt