Metadata-Version: 1.0
Name: HackerNewsAPI
Version: 0.1.1
Summary: A Python wrapper for the Official Hacker News API
Home-page: https://github.com/rpcope1/HackerNewsAPI-Py
Author: Robert P. Cope
Author-email: UNKNOWN
License: LGPL v3
Keywords: ycombinator hacker news
Platform: UNKNOWN
